odoo/addons/sql_export_excel/README.rst
odoo/addons/sql_export_excel/__init__.py
odoo/addons/sql_export_excel/__manifest__.py
odoo/addons/sql_export_excel/i18n/ca.po
odoo/addons/sql_export_excel/i18n/es.po
odoo/addons/sql_export_excel/i18n/it.po
odoo/addons/sql_export_excel/i18n/sql_export_excel.pot
odoo/addons/sql_export_excel/models/__init__.py
odoo/addons/sql_export_excel/models/sql_export.py
odoo/addons/sql_export_excel/readme/CONFIGURE.md
odoo/addons/sql_export_excel/readme/CONTRIBUTORS.md
odoo/addons/sql_export_excel/readme/DESCRIPTION.md
odoo/addons/sql_export_excel/static/description/icon.png
odoo/addons/sql_export_excel/static/description/index.html
odoo/addons/sql_export_excel/tests/__init__.py
odoo/addons/sql_export_excel/tests/test_sql_query_excel.py
odoo/addons/sql_export_excel/views/sql_export_view.xml
odoo_addon_sql_export_excel-18.0.1.0.1.3.dist-info/METADATA
odoo_addon_sql_export_excel-18.0.1.0.1.3.dist-info/WHEEL
odoo_addon_sql_export_excel-18.0.1.0.1.3.dist-info/top_level.txt
odoo_addon_sql_export_excel-18.0.1.0.1.3.dist-info/RECORD
